sent/__init__.py
sent/api.py
sent/telegram.py
sent/types.py
sent/util.py
sent-0.0.20.dist-info/LICENSE
sent-0.0.20.dist-info/METADATA
sent-0.0.20.dist-info/WHEEL
sent-0.0.20.dist-info/top_level.txt
sent-0.0.20.dist-info/RECORD
