Metadata-Version: 2.1
Name: sent
Version: 0.0.20
Summary: A package for sending Telegram messages
Home-page: https://github.com/kalanakt/sent
Author: kalanakt
Author-email: e19198@eng.pdn.ac.lk
License: MIT
Keywords: telegram api
License-File: LICENSE
Requires-Dist: requests
